waymore/__init__.py
waymore/waymore.py
waymore-7.5.dist-info/licenses/LICENSE
waymore-7.5.dist-info/METADATA
waymore-7.5.dist-info/WHEEL
waymore-7.5.dist-info/entry_points.txt
waymore-7.5.dist-info/top_level.txt
waymore-7.5.dist-info/RECORD
