Metadata-Version: 2.4
Name: waymore
Version: 7.5
Summary: Find way more from the Wayback Machine, Common Crawl, Alien Vault OTX, URLScan, VirusTotal & Intelligence X!
Home-page: https://github.com/xnl-h4ck3r/waymore
Author: xnl-h4ck3r
License: MIT
Requires-Python: >=3.9
License-File: LICENSE
Requires-Dist: PyYAML
Requires-Dist: requests
Requires-Dist: setuptools
Requires-Dist: termcolor
Requires-Dist: psutil
Requires-Dist: urlparse3
Requires-Dist: tldextract
Requires-Dist: aiohttp
Dynamic: home-page
Dynamic: license-file
